homekitlink_ffmpeg/__init__.py
homekitlink_ffmpeg/ffmpeg_binaries/arm/ffmpeg
homekitlink_ffmpeg/ffmpeg_binaries/x86/ffmpeg
homekitlink_ffmpeg-0.0.25.dist-info/LICENSE.txt
homekitlink_ffmpeg-0.0.25.dist-info/METADATA
homekitlink_ffmpeg-0.0.25.dist-info/WHEEL
homekitlink_ffmpeg-0.0.25.dist-info/top_level.txt
homekitlink_ffmpeg-0.0.25.dist-info/RECORD
